[{"place_id":248974366,"licence":"Data © OpenStreetMap contributors, ODbL 1.0. http://osm.org/copyright","osm_type":"node","osm_id":245686245,"lat":"19.8772630","lon":"75.3390241","category":"place","type":"city","place_rank":16,"importance":0.5295228475277625,"addresstype":"city","name":"Chhatrapati Sambhajinagar","display_name":"Chhatrapati Sambhajinagar, Chhatrapati Sambhajinagar District, Maharashtra, 431002, India","address":{"city":"Chhatrapati Sambhajinagar","county":"Chhatrapati Sambhajinagar","state_district":"Chhatrapati Sambhajinagar District","state":"Maharashtra","ISO3166-2-lvl4":"IN-MH","postcode":"431002","country":"India","country_code":"in"},"boundingbox":["19.7172630","20.0372630","75.1790241","75.4990241"]}]