[{"place_id":109814927,"licence":"Data © OpenStreetMap contributors, ODbL 1.0. http://osm.org/copyright","osm_type":"relation","osm_id":2712696,"lat":"51.5656819","lon":"4.8296995","category":"boundary","type":"administrative","place_rank":16,"importance":0.36341195681131827,"addresstype":"village","name":"Bavel","display_name":"Bavel, Breda, North Brabant, Netherlands","address":{"village":"Bavel","municipality":"Breda","state":"North Brabant","ISO3166-2-lvl4":"NL-NB","country":"Netherlands","country_code":"nl"},"boundingbox":["51.5478396","51.5834503","4.8074851","4.8716846"]}]