[{"place_id":250789767,"licence":"Data © OpenStreetMap contributors, ODbL 1.0. http://osm.org/copyright","osm_type":"node","osm_id":984080146,"lat":"19.3883898","lon":"85.0496786","category":"place","type":"town","place_rank":18,"importance":0.1600522720683604,"addresstype":"town","name":"Ganjam","display_name":"Ganjam, Odisha, 761027, India","address":{"town":"Ganjam","county":"Ganjam","state_district":"Ganjam","state":"Odisha","ISO3166-2-lvl4":"IN-OD","postcode":"761027","country":"India","country_code":"in"},"boundingbox":["19.3483898","19.4283898","85.0096786","85.0896786"]}]