[{"place_id":369395250,"licence":"Data © OpenStreetMap contributors, ODbL 1.0. http://osm.org/copyright","osm_type":"relation","osm_id":182566,"lat":"40.6356208","lon":"-82.2334709","category":"boundary","type":"administrative","place_rank":16,"importance":0.41395049179757576,"addresstype":"village","name":"Loudonville","display_name":"Loudonville, Hanover Township, Ashland County, Ohio, 44842, United States","address":{"village":"Loudonville","municipality":"Hanover Township","county":"Ashland County","state":"Ohio","ISO3166-2-lvl4":"US-OH","postcode":"44842","country":"United States","country_code":"us"},"boundingbox":["40.6119880","40.6496090","-82.2645130","-82.1995157"]}]