[{"place_id":370223499,"licence":"Data © OpenStreetMap contributors, ODbL 1.0. http://osm.org/copyright","osm_type":"relation","osm_id":182726,"lat":"40.7089380","lon":"-84.3535640","category":"boundary","type":"administrative","place_rank":16,"importance":0.3489254561527194,"addresstype":"village","name":"Spencerville","display_name":"Spencerville, Spencer Township, Allen County, Ohio, United States","address":{"village":"Spencerville","municipality":"Spencer Township","county":"Allen County","state":"Ohio","ISO3166-2-lvl4":"US-OH","country":"United States","country_code":"us"},"boundingbox":["40.6995927","40.7175988","-84.3660251","-84.3395639"]}]