[{"place_id":14598780,"licence":"Data © OpenStreetMap contributors, ODbL 1.0. http://osm.org/copyright","osm_type":"relation","osm_id":301413,"lat":"-6.6123046","lon":"-35.2919016","category":"boundary","type":"administrative","place_rank":16,"importance":0.4612603049670914,"addresstype":"municipality","name":"Jacaraú","display_name":"Jacaraú, Paraíba, Northeast Region, 58278-000, Brazil","address":{"municipality":"Jacaraú","state":"Paraíba","ISO3166-2-lvl4":"BR-PB","region":"Northeast Region","postcode":"58278-000","country":"Brazil","country_code":"br"},"boundingbox":["-6.6954484","-6.5120401","-35.3967272","-35.1444264"]},{"place_id":14562923,"licence":"Data © OpenStreetMap contributors, ODbL 1.0. http://osm.org/copyright","osm_type":"relation","osm_id":6211027,"lat":"-6.5809561","lon":"-35.2977952","category":"boundary","type":"administrative","place_rank":18,"importance":0.16005034943160143,"addresstype":"city_district","name":"Jacaraú","display_name":"Jacaraú, Paraíba, Northeast Region, 58278-000, Brazil","address":{"city_district":"Jacaraú","town":"Jacaraú","state":"Paraíba","ISO3166-2-lvl4":"BR-PB","region":"Northeast Region","postcode":"58278-000","country":"Brazil","country_code":"br"},"boundingbox":["-6.6412713","-6.5120401","-35.3967272","-35.1940067"]}]