[{"place_id":148986450,"licence":"Data © OpenStreetMap contributors, ODbL 1.0. http://osm.org/copyright","osm_type":"node","osm_id":25389641,"lat":"55.6780160","lon":"12.5326186","category":"place","type":"town","place_rank":18,"importance":0.5955876760814289,"addresstype":"town","name":"Frederiksberg","display_name":"Frederiksberg, Frederiksberg Municipality, Capital Region of Denmark, 1861, Denmark","address":{"town":"Frederiksberg","municipality":"Frederiksberg Municipality","state":"Capital Region of Denmark","ISO3166-2-lvl4":"DK-84","postcode":"1861","country":"Denmark","country_code":"dk"},"boundingbox":["55.6380160","55.7180160","12.4926186","12.5726186"]},{"place_id":149352188,"licence":"Data © OpenStreetMap contributors, ODbL 1.0. http://osm.org/copyright","osm_type":"node","osm_id":9599799155,"lat":"55.4157759","lon":"11.5657330","category":"place","type":"village","place_rank":19,"importance":0.23468656939839805,"addresstype":"village","name":"Frederiksberg","display_name":"Frederiksberg, Sorø Municipality, Region Zealand, 4180, Denmark","address":{"village":"Frederiksberg","municipality":"Sorø Municipality","state":"Region Zealand","ISO3166-2-lvl4":"DK-85","postcode":"4180","country":"Denmark","country_code":"dk"},"boundingbox":["55.3957759","55.4357759","11.5457330","11.5857330"]}]