[{"place_id":12741389,"licence":"Data © OpenStreetMap contributors, ODbL 1.0. http://osm.org/copyright","osm_type":"relation","osm_id":334485,"lat":"-14.4361002","lon":"-49.7092915","category":"boundary","type":"administrative","place_rank":16,"importance":0.4905221948955815,"addresstype":"municipality","name":"Santa Terezinha de Goiás","display_name":"Santa Terezinha de Goiás, Goiás, Central-West Region, 76500-000, Brazil","address":{"municipality":"Santa Terezinha de Goiás","state":"Goiás","ISO3166-2-lvl4":"BR-GO","region":"Central-West Region","postcode":"76500-000","country":"Brazil","country_code":"br"},"boundingbox":["-14.6810000","-13.9399198","-49.8971558","-49.4728732"]}]