[{"place_id":19074208,"licence":"Data © OpenStreetMap contributors, ODbL 1.0. http://osm.org/copyright","osm_type":"relation","osm_id":6458620,"lat":"-34.2532589","lon":"140.4579655","category":"boundary","type":"administrative","place_rank":18,"importance":0.2782362227145218,"addresstype":"town","name":"Barmera","display_name":"Barmera, South Australia, 5345, Australia","address":{"town":"Barmera","state":"South Australia","ISO3166-2-lvl4":"AU-SA","postcode":"5345","country":"Australia","country_code":"au"},"boundingbox":["-34.2856469","-34.1796222","140.4179706","140.5242797"]}]