[{"place_id":8396540,"licence":"Data © OpenStreetMap contributors, ODbL 1.0. http://osm.org/copyright","osm_type":"relation","osm_id":298535,"lat":"-23.6397400","lon":"-47.8248630","category":"boundary","type":"administrative","place_rank":16,"importance":0.5313330276421782,"addresstype":"municipality","name":"Sarapuí","display_name":"Sarapuí, São Paulo, Southeast Region, 18225-000, Brazil","address":{"municipality":"Sarapuí","state":"São Paulo","ISO3166-2-lvl4":"BR-SP","region":"Southeast Region","postcode":"18225-000","country":"Brazil","country_code":"br"},"boundingbox":["-23.7655732","-23.5316754","-47.9176266","-47.6370000"]},{"place_id":8386123,"licence":"Data © OpenStreetMap contributors, ODbL 1.0. http://osm.org/copyright","osm_type":"relation","osm_id":5684952,"lat":"-23.6485380","lon":"-47.8004457","category":"boundary","type":"administrative","place_rank":18,"importance":0.16005836041809718,"addresstype":"city_district","name":"Sarapuí","display_name":"Sarapuí, São Paulo, Southeast Region, 18225-000, Brazil","address":{"city_district":"Sarapuí","town":"Sarapuí","state":"São Paulo","ISO3166-2-lvl4":"BR-SP","region":"Southeast Region","postcode":"18225-000","country":"Brazil","country_code":"br"},"boundingbox":["-23.7655732","-23.5316754","-47.9176266","-47.7014762"]}]