[{"place_id":59034120,"licence":"Data © OpenStreetMap contributors, ODbL 1.0. http://osm.org/copyright","osm_type":"node","osm_id":273488704,"lat":"41.3809141","lon":"25.0950002","category":"place","type":"town","place_rank":18,"importance":0.4831324273129615,"addresstype":"town","name":"Zlatograd","display_name":"Zlatograd, Smolyan, 4980, Bulgaria","address":{"town":"Zlatograd","state_district":"Zlatograd","state":"Smolyan","ISO3166-2-lvl4":"BG-21","postcode":"4980","country":"Bulgaria","country_code":"bg"},"boundingbox":["41.3409141","41.4209141","25.0550002","25.1350002"]}]