[{"place_id":122141372,"licence":"Data © OpenStreetMap contributors, ODbL 1.0. http://osm.org/copyright","osm_type":"relation","osm_id":14506519,"lat":"48.5870620","lon":"9.1817914","category":"boundary","type":"administrative","place_rank":20,"importance":0.17283327415591612,"addresstype":"village","name":"Walddorf","display_name":"Walddorf, Walddorfhäslach, VVG der Gemeinde Pliezhausen, Landkreis Reutlingen, Baden-Württemberg, 72141, Germany","address":{"village":"Walddorf","municipality":"Walddorfhäslach","county":"Landkreis Reutlingen","state":"Baden-Württemberg","ISO3166-2-lvl4":"DE-BW","postcode":"72141","country":"Germany","country_code":"de"},"boundingbox":["48.5732562","48.6048288","9.1187328","9.2071418"]},{"place_id":123331308,"licence":"Data © OpenStreetMap contributors, ODbL 1.0. http://osm.org/copyright","osm_type":"node","osm_id":36771173,"lat":"48.5758288","lon":"8.6497332","category":"place","type":"village","place_rank":19,"importance":0.17283327415591612,"addresstype":"village","name":"Walddorf","display_name":"Walddorf, Altensteig, VVG der Stadt Altensteig, Landkreis Calw, Baden-Württemberg, 72213, Germany","address":{"village":"Walddorf","town":"Altensteig","municipality":"VVG der Stadt Altensteig","county":"Landkreis Calw","state":"Baden-Württemberg","ISO3166-2-lvl4":"DE-BW","postcode":"72213","country":"Germany","country_code":"de"},"boundingbox":["48.5558288","48.5958288","8.6297332","8.6697332"]}]