[{"place_id":278121829,"licence":"Data © OpenStreetMap contributors, ODbL 1.0. http://osm.org/copyright","osm_type":"relation","osm_id":957426,"lat":"53.2684565","lon":"-0.8366218","category":"boundary","type":"administrative","place_rank":20,"importance":0.33359242145229745,"addresstype":"suburb","name":"East Drayton","display_name":"East Drayton, Bassetlaw, Nottinghamshire, East Midlands, England, United Kingdom","address":{"suburb":"East Drayton","city":"Bassetlaw","county":"Nottinghamshire","ISO3166-2-lvl6":"GB-NTT","state_district":"East Midlands","state":"England","ISO3166-2-lvl4":"GB-ENG","country":"United Kingdom","country_code":"gb"},"boundingbox":["53.2547280","53.2820761","-0.8615267","-0.8156907"]},{"place_id":278177528,"licence":"Data © OpenStreetMap contributors, ODbL 1.0. http://osm.org/copyright","osm_type":"node","osm_id":3168460596,"lat":"53.2689137","lon":"-0.8373142","category":"place","type":"village","place_rank":19,"importance":0.14671845349813073,"addresstype":"village","name":"East Drayton","display_name":"East Drayton, Bassetlaw, Nottinghamshire, East Midlands, England, DN22 0LF, United Kingdom","address":{"village":"East Drayton","city":"Bassetlaw","county":"Nottinghamshire","ISO3166-2-lvl6":"GB-NTT","state_district":"East Midlands","state":"England","ISO3166-2-lvl4":"GB-ENG","postcode":"DN22 0LF","country":"United Kingdom","country_code":"gb"},"boundingbox":["53.2489137","53.2889137","-0.8573142","-0.8173142"]}]