[{"place_id":286060291,"licence":"Data © OpenStreetMap contributors, ODbL 1.0. http://osm.org/copyright","osm_type":"relation","osm_id":13599885,"lat":"47.7852436","lon":"-53.8434879","category":"natural","type":"bay","place_rank":22,"importance":0.10667666666666664,"addresstype":"bay","name":"Bull Arm","display_name":"Bull Arm, Sunnyside, Unincorporated Newfoundland, Newfoundland, Newfoundland and Labrador, Canada","address":{"bay":"Bull Arm","town":"Sunnyside","county":"Unincorporated Newfoundland","state_district":"Newfoundland","state":"Newfoundland and Labrador","ISO3166-2-lvl4":"CA-NL","country":"Canada","country_code":"ca"},"boundingbox":["47.7183256","47.8521392","-53.8942976","-53.7993221"]}]