[{"place_id":129910232,"licence":"Data © OpenStreetMap contributors, ODbL 1.0. http://osm.org/copyright","osm_type":"relation","osm_id":406436,"lat":"48.4535595","lon":"15.0393918","category":"boundary","type":"administrative","place_rank":16,"importance":0.3943200352487266,"addresstype":"village","name":"Schönbach","display_name":"Schönbach, Bezirk Zwettl, Lower Austria, 3633, Austria","address":{"village":"Schönbach","county":"Bezirk Zwettl","state":"Lower Austria","ISO3166-2-lvl4":"AT-3","postcode":"3633","country":"Austria","country_code":"at"},"boundingbox":["48.4203002","48.4858305","14.9946433","15.1237648"]},{"place_id":69995759,"licence":"Data © OpenStreetMap contributors, ODbL 1.0. http://osm.org/copyright","osm_type":"node","osm_id":3781987363,"lat":"47.9209583","lon":"13.6385316","category":"place","type":"hamlet","place_rank":20,"importance":0.13338397726405735,"addresstype":"hamlet","name":"Schönbach","display_name":"Schönbach, Schörfling am Attersee, Bezirk Vöcklabruck, Upper Austria, 4861, Austria","address":{"hamlet":"Schönbach","village":"Schörfling am Attersee","county":"Bezirk Vöcklabruck","state":"Upper Austria","ISO3166-2-lvl4":"AT-4","postcode":"4861","country":"Austria","country_code":"at"},"boundingbox":["47.9009583","47.9409583","13.6185316","13.6585316"]},{"place_id":69584851,"licence":"Data © OpenStreetMap contributors, ODbL 1.0. http://osm.org/copyright","osm_type":"node","osm_id":240076397,"lat":"47.2514383","lon":"12.3094661","category":"place","type":"hamlet","place_rank":20,"importance":0.13338267719539176,"addresstype":"hamlet","name":"Schönbach","display_name":"Schönbach, Bramberg am Wildkogel, Bezirk Zell am See, Salzburg, 5733, Austria","address":{"hamlet":"Schönbach","village":"Bramberg am Wildkogel","county":"Bezirk Zell am See","state":"Salzburg","ISO3166-2-lvl4":"AT-5","postcode":"5733","country":"Austria","country_code":"at"},"boundingbox":["47.2314383","47.2714383","12.2894661","12.3294661"]},{"place_id":129003050,"licence":"Data © OpenStreetMap contributors, ODbL 1.0. http://osm.org/copyright","osm_type":"node","osm_id":240109596,"lat":"48.5191130","lon":"13.5338688","category":"place","type":"hamlet","place_rank":20,"importance":0.13338102769512472,"addresstype":"hamlet","name":"Schönbach","display_name":"Schönbach, Schardenberg, Bezirk Schärding, Upper Austria, 4784, Austria","address":{"hamlet":"Schönbach","village":"Schardenberg","county":"Bezirk Schärding","state":"Upper Austria","ISO3166-2-lvl4":"AT-4","postcode":"4784","country":"Austria","country_code":"at"},"boundingbox":["48.4991130","48.5391130","13.5138688","13.5538688"]},{"place_id":129844582,"licence":"Data © OpenStreetMap contributors, ODbL 1.0. http://osm.org/copyright","osm_type":"relation","osm_id":19531339,"lat":"48.4535494","lon":"15.0375043","category":"boundary","type":"administrative","place_rank":20,"importance":0.13337999313344012,"addresstype":"suburb","name":"Katastralgemeinde Schönbach","display_name":"Katastralgemeinde Schönbach, Schönbach, Bezirk Zwettl, Lower Austria, Austria","address":{"suburb":"Katastralgemeinde Schönbach","village":"Schönbach","county":"Bezirk Zwettl","state":"Lower Austria","ISO3166-2-lvl4":"AT-3","country":"Austria","country_code":"at"},"boundingbox":["48.4388878","48.4681806","14.9976036","15.0750785"]},{"place_id":69707981,"licence":"Data © OpenStreetMap contributors, ODbL 1.0. http://osm.org/copyright","osm_type":"node","osm_id":8828266548,"lat":"47.7089736","lon":"13.1947700","category":"place","type":"farm","place_rank":22,"importance":0.10671152590218964,"addresstype":"farm","name":"Schönbach","display_name":"Schönbach, Schattseite, Gaißau, Krispl, Bezirk Hallein, Salzburg, 5421, Austria","address":{"farm":"Schönbach","hamlet":"Schattseite","village":"Gaißau","county":"Bezirk Hallein","state":"Salzburg","ISO3166-2-lvl4":"AT-5","postcode":"5421","country":"Austria","country_code":"at"},"boundingbox":["47.6989736","47.7189736","13.1847700","13.2047700"]}]