[{"place_id":210978957,"licence":"Data © OpenStreetMap contributors, ODbL 1.0. http://osm.org/copyright","osm_type":"relation","osm_id":8475054,"lat":"32.2812350","lon":"35.9010013","category":"place","type":"town","place_rank":18,"importance":0.5047396499895902,"addresstype":"town","name":"Jerash","display_name":"Jerash, Jerash Sub-District, Qasabah Jerash, Jarash, Jordan","address":{"town":"Jerash","county":"Jerash Sub-District","state_district":"Qasabah Jerash","state":"Jarash","ISO3166-2-lvl4":"JO-JA","country":"Jordan","country_code":"jo"},"boundingbox":["32.2683147","32.2981792","35.8768844","35.9125601"]}]