[{"place_id":274618233,"licence":"Data © OpenStreetMap contributors, ODbL 1.0. http://osm.org/copyright","osm_type":"relation","osm_id":7034228,"lat":"52.4198250","lon":"-2.9266206","category":"boundary","type":"administrative","place_rank":20,"importance":0.35699141996923245,"addresstype":"village","name":"Clunbury","display_name":"Clunbury, Shropshire, England, United Kingdom","address":{"village":"Clunbury","county":"Shropshire","ISO3166-2-lvl6":"GB-SHR","state":"England","ISO3166-2-lvl4":"GB-ENG","country":"United Kingdom","country_code":"gb"},"boundingbox":["52.3893732","52.4554793","-3.0114780","-2.8877711"]}]