[{"place_id":358825180,"licence":"Data © OpenStreetMap contributors, ODbL 1.0. http://osm.org/copyright","osm_type":"node","osm_id":158496172,"lat":"42.2731296","lon":"-76.1479840","category":"place","type":"hamlet","place_rank":20,"importance":0.1333833348592355,"addresstype":"hamlet","name":"New Connecticut","display_name":"New Connecticut, Town of Newark Valley, Tioga County, New York, 13881, United States","address":{"hamlet":"New Connecticut","village":"Town of Newark Valley","county":"Tioga County","state":"New York","ISO3166-2-lvl4":"US-NY","postcode":"13881","country":"United States","country_code":"us"},"boundingbox":["42.2531296","42.2931296","-76.1679840","-76.1279840"]}]