[{"place_id":294511120,"licence":"Data © OpenStreetMap contributors, ODbL 1.0. http://osm.org/copyright","osm_type":"relation","osm_id":347877,"lat":"38.9481556","lon":"-0.6492732","category":"boundary","type":"administrative","place_rank":16,"importance":0.5156461248898018,"addresstype":"village","name":"Montesa","display_name":"Montesa, la Costera, Valencia, Valencian Community, 46692, Spain","address":{"village":"Montesa","region":"la Costera","province":"Valencia","ISO3166-2-lvl6":"ES-V","state":"Valencian Community","ISO3166-2-lvl4":"ES-VC","postcode":"46692","country":"Spain","country_code":"es"},"boundingbox":["38.8902095","38.9813437","-0.7000551","-0.5963680"]}]