[{"place_id":159895558,"licence":"Data © OpenStreetMap contributors, ODbL 1.0. http://osm.org/copyright","osm_type":"node","osm_id":9988868939,"lat":"59.4426155","lon":"5.7447049","category":"place","type":"hamlet","place_rank":20,"importance":0.13338525902189668,"addresstype":"hamlet","name":"Raunes","display_name":"Raunes, Vindafjord, Rogaland, 5578, Norway","address":{"hamlet":"Raunes","municipality":"Vindafjord","county":"Rogaland","ISO3166-2-lvl4":"NO-11","postcode":"5578","country":"Norway","country_code":"no"},"boundingbox":["59.4226155","59.4626155","5.7247049","5.7647049"]},{"place_id":159996336,"licence":"Data © OpenStreetMap contributors, ODbL 1.0. http://osm.org/copyright","osm_type":"node","osm_id":713223567,"lat":"59.4538333","lon":"5.7319684","category":"place","type":"locality","place_rank":25,"importance":0.06671859235523002,"addresstype":"locality","name":"Raunes","display_name":"Raunes, Eikanes, Vindafjord, Rogaland, 5578, Norway","address":{"locality":"Raunes","hamlet":"Eikanes","municipality":"Vindafjord","county":"Rogaland","ISO3166-2-lvl4":"NO-11","postcode":"5578","country":"Norway","country_code":"no"},"boundingbox":["59.4438333","59.4638333","5.7219684","5.7419684"]},{"place_id":160099021,"licence":"Data © OpenStreetMap contributors, ODbL 1.0. http://osm.org/copyright","osm_type":"node","osm_id":6373614220,"lat":"59.4423790","lon":"5.7458070","category":"highway","type":"bus_stop","place_rank":30,"importance":5.192568856331758e-05,"addresstype":"highway","name":"Raunes","display_name":"Raunes, Raunesvegen, Raunes, Vindafjord, Rogaland, 5578, Norway","address":{"highway":"Raunes","road":"Raunesvegen","hamlet":"Raunes","municipality":"Vindafjord","county":"Rogaland","ISO3166-2-lvl4":"NO-11","postcode":"5578","country":"Norway","country_code":"no"},"boundingbox":["59.4423290","59.4424290","5.7457570","5.7458570"]}]