[{"place_id":169881970,"licence":"Data © OpenStreetMap contributors, ODbL 1.0. http://osm.org/copyright","osm_type":"relation","osm_id":352372,"lat":"59.4551194","lon":"26.8680733","category":"boundary","type":"administrative","place_rank":18,"importance":0.4276151273745538,"addresstype":"city_district","name":"Aseri alevik","display_name":"Aseri alevik, Viru-Nigula vald, Lääne-Viru County, 43401, Estonia","address":{"city_district":"Aseri alevik","municipality":"Viru-Nigula vald","ISO3166-2-lvl7":"EE-903","county":"Lääne-Viru County","ISO3166-2-lvl6":"EE-60","postcode":"43401","country":"Estonia","country_code":"ee"},"boundingbox":["59.4444806","59.4654922","26.8488745","26.8944354"]},{"place_id":170018416,"licence":"Data © OpenStreetMap contributors, ODbL 1.0. http://osm.org/copyright","osm_type":"node","osm_id":28863835,"lat":"59.4521441","lon":"26.8662369","category":"place","type":"village","place_rank":19,"importance":0.1467164225223163,"addresstype":"village","name":"Aseri","display_name":"Aseri, Viru-Nigula vald, Lääne-Viru County, 43401, Estonia","address":{"village":"Aseri","municipality":"Viru-Nigula vald","ISO3166-2-lvl7":"EE-903","county":"Lääne-Viru County","ISO3166-2-lvl6":"EE-60","postcode":"43401","country":"Estonia","country_code":"ee"},"boundingbox":["59.4321441","59.4721441","26.8462369","26.8862369"]}]