[{"place_id":104856779,"licence":"Data © OpenStreetMap contributors, ODbL 1.0. http://osm.org/copyright","osm_type":"relation","osm_id":19013290,"lat":"50.4984249","lon":"5.0805501","category":"boundary","type":"administrative","place_rank":16,"importance":0.359473463574925,"addresstype":"village","name":"Seilles","display_name":"Seilles, Andenne, Namur, Wallonia, Belgium","address":{"village":"Seilles","town":"Andenne","county":"Namur","state":"Namur","ISO3166-2-lvl6":"BE-WNA","ISO3166-2-lvl4":"BE-WAL","country":"Belgium","country_code":"be"},"boundingbox":["50.4922233","50.5185290","5.0345736","5.1449391"]}]