[{"place_id":238068752,"licence":"Data © OpenStreetMap contributors, ODbL 1.0. http://osm.org/copyright","osm_type":"way","osm_id":221120161,"lat":"16.8978868","lon":"99.2545255","category":"aeroway","type":"aerodrome","place_rank":30,"importance":0.32592895108882386,"addresstype":"aeroway","name":"Tak Airport","display_name":"Tak Airport, Charot Withi Thong Road, Ban Sanam Bin Mai, Ban Khlong Sak, Nong Bua Tai, Mueang Tak District, Tak Province, Thailand","address":{"aeroway":"Tak Airport","road":"Charot Withi Thong Road","hamlet":"Ban Sanam Bin Mai","village":"Ban Khlong Sak","municipality":"Nong Bua Tai","county":"Mueang Tak District","province":"Tak Province","ISO3166-2-lvl4":"TH-63","country":"Thailand","country_code":"th"},"boundingbox":["16.8933124","16.9017263","99.2390051","99.2667652"]}]