[{"place_id":74921800,"licence":"Data © OpenStreetMap contributors, ODbL 1.0. http://osm.org/copyright","osm_type":"node","osm_id":407927374,"lat":"45.7014937","lon":"10.3871802","category":"place","type":"village","place_rank":19,"importance":0.18929199030239088,"addresstype":"village","name":"Nozza","display_name":"Nozza, Vestone, Comunità montana della Valle Sabbia, Brescia, Lombardy, 25078, Italy","address":{"village":"Nozza","municipality":"Comunità montana della Valle Sabbia","county":"Brescia","ISO3166-2-lvl6":"IT-BS","state":"Lombardy","ISO3166-2-lvl4":"IT-25","postcode":"25078","country":"Italy","country_code":"it"},"boundingbox":["45.6814937","45.7214937","10.3671802","10.4071802"]},{"place_id":74660117,"licence":"Data © OpenStreetMap contributors, ODbL 1.0. http://osm.org/copyright","osm_type":"way","osm_id":434743360,"lat":"45.7067383","lon":"10.3918568","category":"landuse","type":"industrial","place_rank":24,"importance":0.08006237659266038,"addresstype":"industrial","name":"Nozza","display_name":"Nozza, Mocenigo, Nozza, Vestone, Comunità montana della Valle Sabbia, Brescia, Lombardy, 25078, Italy","address":{"industrial":"Nozza","hamlet":"Mocenigo","village":"Nozza","municipality":"Comunità montana della Valle Sabbia","county":"Brescia","ISO3166-2-lvl6":"IT-BS","state":"Lombardy","ISO3166-2-lvl4":"IT-25","postcode":"25078","country":"Italy","country_code":"it"},"boundingbox":["45.7062184","45.7070985","10.3912141","10.3923604"]}]