[{"place_id":378411061,"licence":"Data © OpenStreetMap contributors, ODbL 1.0. http://osm.org/copyright","osm_type":"relation","osm_id":16770627,"lat":"62.9563889","lon":"-155.5958330","category":"boundary","type":"administrative","place_rank":16,"importance":0.4265549189732791,"addresstype":"village","name":"McGrath","display_name":"McGrath, Unorganized Borough, Alaska, 99627, United States","address":{"village":"McGrath","county":"Unorganized Borough","state":"Alaska","ISO3166-2-lvl4":"US-AK","postcode":"99627","country":"United States","country_code":"us"},"boundingbox":["62.8990460","62.9856970","-155.6897070","-155.4363070"]}]