[{"place_id":52511310,"licence":"Data © OpenStreetMap contributors, ODbL 1.0. http://osm.org/copyright","osm_type":"relation","osm_id":545892,"lat":"36.7420067","lon":"3.0665715","category":"boundary","type":"administrative","place_rank":16,"importance":0.4194818330375235,"addresstype":"suburb","name":"El Madania","display_name":"El Madania, Algiers, Sidi M'Hamed District, Algiers, 16000, Algeria","address":{"suburb":"El Madania","city":"Algiers","county":"Sidi M'Hamed District","state":"Algiers","ISO3166-2-lvl4":"DZ-16","postcode":"16000","country":"Algeria","country_code":"dz"},"boundingbox":["36.7340282","36.7504980","3.0528560","3.0852416"]}]