[{"place_id":355120147,"licence":"Data © OpenStreetMap contributors, ODbL 1.0. http://osm.org/copyright","osm_type":"relation","osm_id":2027464,"lat":"43.4065066","lon":"-72.4076233","category":"boundary","type":"administrative","place_rank":16,"importance":0.43106034210224703,"addresstype":"hamlet","name":"Weathersfield","display_name":"Weathersfield, Windsor County, Vermont, United States","address":{"hamlet":"Weathersfield","county":"Windsor County","state":"Vermont","ISO3166-2-lvl4":"US-VT","country":"United States","country_code":"us"},"boundingbox":["43.3382104","43.4435419","-72.5454805","-72.3899519"]}]