[{"place_id":147358884,"licence":"Data © OpenStreetMap contributors, ODbL 1.0. http://osm.org/copyright","osm_type":"relation","osm_id":1433093,"lat":"53.9404498","lon":"14.0729189","category":"boundary","type":"administrative","place_rank":16,"importance":0.49153869809411044,"addresstype":"village","name":"Benz","display_name":"Benz, Usedom-Süd, Vorpommern-Greifswald, Mecklenburg-Vorpommern, 17429, Germany","address":{"village":"Benz","municipality":"Usedom-Süd","county":"Vorpommern-Greifswald","state":"Mecklenburg-Vorpommern","ISO3166-2-lvl4":"DE-MV","postcode":"17429","country":"Germany","country_code":"de"},"boundingbox":["53.9078400","53.9629439","13.9847916","14.1197174"]},{"place_id":152226279,"licence":"Data © OpenStreetMap contributors, ODbL 1.0. http://osm.org/copyright","osm_type":"relation","osm_id":1515588,"lat":"53.9111309","lon":"11.5827550","category":"boundary","type":"administrative","place_rank":16,"importance":0.4573721351816049,"addresstype":"village","name":"Benz","display_name":"Benz, Neuburg, Nordwestmecklenburg, Mecklenburg-Vorpommern, Germany","address":{"village":"Benz","municipality":"Neuburg","county":"Nordwestmecklenburg","state":"Mecklenburg-Vorpommern","ISO3166-2-lvl4":"DE-MV","country":"Germany","country_code":"de"},"boundingbox":["53.8862951","53.9374532","11.5524159","11.6514964"]},{"place_id":143452972,"licence":"Data © OpenStreetMap contributors, ODbL 1.0. http://osm.org/copyright","osm_type":"node","osm_id":448929981,"lat":"53.2462083","lon":"11.1208688","category":"place","type":"hamlet","place_rank":20,"importance":0.13338970702677957,"addresstype":"hamlet","name":"Benz","display_name":"Benz, Lübtheen, Ludwigslust-Parchim, Mecklenburg-Vorpommern, 19249, Germany","address":{"hamlet":"Benz","town":"Lübtheen","county":"Ludwigslust-Parchim","state":"Mecklenburg-Vorpommern","ISO3166-2-lvl4":"DE-MV","postcode":"19249","country":"Germany","country_code":"de"},"boundingbox":["53.2262083","53.2662083","11.1008688","11.1408688"]},{"place_id":147804067,"licence":"Data © OpenStreetMap contributors, ODbL 1.0. http://osm.org/copyright","osm_type":"node","osm_id":331602173,"lat":"54.2962199","lon":"13.2415663","category":"place","type":"hamlet","place_rank":20,"importance":0.13338650720988782,"addresstype":"hamlet","name":"Benz","display_name":"Benz, Gustow, Bergen auf Rügen, Vorpommern-Rügen, Mecklenburg-Vorpommern, 18574, Germany","address":{"hamlet":"Benz","village":"Gustow","municipality":"Bergen auf Rügen","county":"Vorpommern-Rügen","state":"Mecklenburg-Vorpommern","ISO3166-2-lvl4":"DE-MV","postcode":"18574","country":"Germany","country_code":"de"},"boundingbox":["54.2762199","54.3162199","13.2215663","13.2615663"]}]