[{"place_id":374741589,"licence":"Data © OpenStreetMap contributors, ODbL 1.0. http://osm.org/copyright","osm_type":"node","osm_id":9750201136,"lat":"50.6238521","lon":"-99.4622386","category":"place","type":"village","place_rank":19,"importance":0.14671012970168607,"addresstype":"village","name":"Kelwood","display_name":"Kelwood, Rural Municipality of Rosedale, Manitoba, R0J 0Y0, Canada","address":{"village":"Kelwood","county":"Rural Municipality of Rosedale","state":"Manitoba","ISO3166-2-lvl4":"CA-MB","postcode":"R0J 0Y0","country":"Canada","country_code":"ca"},"boundingbox":["50.6038521","50.6438521","-99.4822386","-99.4422386"]},{"place_id":375287035,"licence":"Data © OpenStreetMap contributors, ODbL 1.0. http://osm.org/copyright","osm_type":"way","osm_id":79793874,"lat":"50.6230560","lon":"-99.4626524","category":"landuse","type":"residential","place_rank":24,"importance":0.08004346303501943,"addresstype":"residential","name":"Kelwood","display_name":"Kelwood, Rural Municipality of Rosedale, Manitoba, R0J 0Y0, Canada","address":{"residential":"Kelwood","village":"Kelwood","county":"Rural Municipality of Rosedale","state":"Manitoba","ISO3166-2-lvl4":"CA-MB","postcode":"R0J 0Y0","country":"Canada","country_code":"ca"},"boundingbox":["50.6204124","50.6255178","-99.4661565","-99.4586334"]}]