[{"place_id":15095005,"licence":"Data © OpenStreetMap contributors, ODbL 1.0. http://osm.org/copyright","osm_type":"relation","osm_id":303802,"lat":"-9.7496551","lon":"-37.4329891","category":"boundary","type":"administrative","place_rank":16,"importance":0.45700694538322234,"addresstype":"municipality","name":"Pão de Açúcar","display_name":"Pão de Açúcar, Alagoas, Northeast Region, 57400-000, Brazil","address":{"municipality":"Pão de Açúcar","state":"Alagoas","ISO3166-2-lvl4":"BR-AL","region":"Northeast Region","postcode":"57400-000","country":"Brazil","country_code":"br"},"boundingbox":["-9.8316392","-9.4976354","-37.6704634","-37.2404621"]},{"place_id":15080306,"licence":"Data © OpenStreetMap contributors, ODbL 1.0. http://osm.org/copyright","osm_type":"relation","osm_id":6186619,"lat":"-9.6424145","lon":"-37.5617361","category":"boundary","type":"administrative","place_rank":18,"importance":0.1600546051728084,"addresstype":"city_district","name":"Pão de Açúcar","display_name":"Pão de Açúcar, Alagoas, Northeast Region, 57400-000, Brazil","address":{"city_district":"Pão de Açúcar","town":"Pão de Açúcar","state":"Alagoas","ISO3166-2-lvl4":"BR-AL","region":"Northeast Region","postcode":"57400-000","country":"Brazil","country_code":"br"},"boundingbox":["-9.7872921","-9.4976354","-37.6704634","-37.3030574"]}]