[{"place_id":161540797,"licence":"Data © OpenStreetMap contributors, ODbL 1.0. http://osm.org/copyright","osm_type":"relation","osm_id":7555528,"lat":"63.3216469","lon":"10.4742217","category":"boundary","type":"administrative","place_rank":18,"importance":0.36391963791291315,"addresstype":"city_district","name":"Heimdal","display_name":"Heimdal, Trondheim, Trøndelag, Norway","address":{"city_district":"Heimdal","city":"Trondheim","county":"Trøndelag","ISO3166-2-lvl4":"NO-50","country":"Norway","country_code":"no"},"boundingbox":["63.1598985","63.4833678","10.0035259","10.7251987"]},{"place_id":161572679,"licence":"Data © OpenStreetMap contributors, ODbL 1.0. http://osm.org/copyright","osm_type":"node","osm_id":59258056,"lat":"63.3513320","lon":"10.3564310","category":"place","type":"suburb","place_rank":19,"importance":0.14673969405661091,"addresstype":"suburb","name":"Heimdal","display_name":"Heimdal, Trondheim, Trøndelag, 7072, Norway","address":{"suburb":"Heimdal","city_district":"Heimdal","city":"Trondheim","county":"Trøndelag","ISO3166-2-lvl4":"NO-50","postcode":"7072","country":"Norway","country_code":"no"},"boundingbox":["63.3313320","63.3713320","10.3364310","10.3764310"]},{"place_id":161586455,"licence":"Data © OpenStreetMap contributors, ODbL 1.0. http://osm.org/copyright","osm_type":"node","osm_id":9907521481,"lat":"63.9447167","lon":"11.5352388","category":"place","type":"farm","place_rank":22,"importance":0.10672598840314333,"addresstype":"farm","name":"Heimdal","display_name":"Heimdal, Rokka, Steinkjer, Trøndelag, 7711, Norway","address":{"farm":"Heimdal","hamlet":"Rokka","municipality":"Steinkjer","county":"Trøndelag","ISO3166-2-lvl4":"NO-50","postcode":"7711","country":"Norway","country_code":"no"},"boundingbox":["63.9347167","63.9547167","11.5252388","11.5452388"]},{"place_id":273417984,"licence":"Data © OpenStreetMap contributors, ODbL 1.0. http://osm.org/copyright","osm_type":"node","osm_id":9907520049,"lat":"64.0630784","lon":"11.2062521","category":"place","type":"farm","place_rank":22,"importance":0.10672598840314333,"addresstype":"farm","name":"Heimdal","display_name":"Heimdal, Haugan, Brattreit, Malm, Steinkjer, Trøndelag, 7790, Norway","address":{"farm":"Heimdal","neighbourhood":"Haugan","hamlet":"Brattreit","village":"Malm","municipality":"Steinkjer","county":"Trøndelag","ISO3166-2-lvl4":"NO-50","postcode":"7790","country":"Norway","country_code":"no"},"boundingbox":["64.0530784","64.0730784","11.1962521","11.2162521"]},{"place_id":273263940,"licence":"Data © OpenStreetMap contributors, ODbL 1.0. http://osm.org/copyright","osm_type":"node","osm_id":9899020480,"lat":"64.6326444","lon":"11.2832555","category":"place","type":"farm","place_rank":22,"importance":0.1067245021744106,"addresstype":"farm","name":"Heimdal","display_name":"Heimdal, Namsos, Trøndelag, 7856, Norway","address":{"farm":"Heimdal","municipality":"Namsos","county":"Trøndelag","ISO3166-2-lvl4":"NO-50","postcode":"7856","country":"Norway","country_code":"no"},"boundingbox":["64.6226444","64.6426444","11.2732555","11.2932555"]},{"place_id":273350651,"licence":"Data © OpenStreetMap contributors, ODbL 1.0. http://osm.org/copyright","osm_type":"node","osm_id":9899020303,"lat":"64.5330334","lon":"11.5536834","category":"place","type":"farm","place_rank":22,"importance":0.1067245021744106,"addresstype":"farm","name":"Heimdal","display_name":"Heimdal, Sørenget, Namsos, Trøndelag, 7810, Norway","address":{"farm":"Heimdal","hamlet":"Sørenget","municipality":"Namsos","county":"Trøndelag","ISO3166-2-lvl4":"NO-50","postcode":"7810","country":"Norway","country_code":"no"},"boundingbox":["64.5230334","64.5430334","11.5436834","11.5636834"]},{"place_id":270544522,"licence":"Data © OpenStreetMap contributors, ODbL 1.0. http://osm.org/copyright","osm_type":"node","osm_id":9899020656,"lat":"64.5266528","lon":"11.3062279","category":"place","type":"farm","place_rank":22,"importance":0.1067245021744106,"addresstype":"farm","name":"Heimdal","display_name":"Heimdal, Vindsetmoan, Namsos, Trøndelag, 7819, Norway","address":{"farm":"Heimdal","hamlet":"Vindsetmoan","municipality":"Namsos","county":"Trøndelag","ISO3166-2-lvl4":"NO-50","postcode":"7819","country":"Norway","country_code":"no"},"boundingbox":["64.5166528","64.5366528","11.2962279","11.3162279"]},{"place_id":271548108,"licence":"Data © OpenStreetMap contributors, ODbL 1.0. http://osm.org/copyright","osm_type":"node","osm_id":9817040970,"lat":"64.2742337","lon":"12.4703776","category":"place","type":"farm","place_rank":22,"importance":0.10672124437323566,"addresstype":"farm","name":"Heimdal","display_name":"Heimdal, Ryggvoll, Snåsa, Trøndelag, Norway","address":{"farm":"Heimdal","hamlet":"Ryggvoll","municipality":"Snåsa","county":"Trøndelag","ISO3166-2-lvl4":"NO-50","country":"Norway","country_code":"no"},"boundingbox":["64.2642337","64.2842337","12.4603776","12.4803776"]},{"place_id":161795503,"licence":"Data © OpenStreetMap contributors, ODbL 1.0. http://osm.org/copyright","osm_type":"node","osm_id":9908936674,"lat":"63.6879259","lon":"11.0958133","category":"place","type":"farm","place_rank":22,"importance":0.10671666819256884,"addresstype":"farm","name":"Heimdal","display_name":"Heimdal, Jørås, Levanger, Trøndelag, 7623, Norway","address":{"farm":"Heimdal","hamlet":"Jørås","municipality":"Levanger","county":"Trøndelag","ISO3166-2-lvl4":"NO-50","postcode":"7623","country":"Norway","country_code":"no"},"boundingbox":["63.6779259","63.6979259","11.0858133","11.1058133"]},{"place_id":270182279,"licence":"Data © OpenStreetMap contributors, ODbL 1.0. http://osm.org/copyright","osm_type":"node","osm_id":9907520727,"lat":"64.0534944","lon":"11.1310056","category":"place","type":"farm","place_rank":22,"importance":0.10672598840314333,"addresstype":"farm","name":"Heimstad","display_name":"Heimstad, Brenna, Steinkjer, Trøndelag, 7790, Norway","address":{"farm":"Heimstad","hamlet":"Brenna","municipality":"Steinkjer","county":"Trøndelag","ISO3166-2-lvl4":"NO-50","postcode":"7790","country":"Norway","country_code":"no"},"boundingbox":["64.0434944","64.0634944","11.1210056","11.1410056"]}]