[{"place_id":115339180,"licence":"Data © OpenStreetMap contributors, ODbL 1.0. http://osm.org/copyright","osm_type":"relation","osm_id":451707,"lat":"50.6347014","lon":"7.9179599","category":"boundary","type":"administrative","place_rank":16,"importance":0.5137235145934684,"addresstype":"village","name":"Hardt","display_name":"Hardt, Bad Marienberg (Westerwald), Westerwaldkreis, Rhineland-Palatinate, Germany","address":{"village":"Hardt","municipality":"Bad Marienberg (Westerwald)","county":"Westerwaldkreis","state":"Rhineland-Palatinate","ISO3166-2-lvl4":"DE-RP","country":"Germany","country_code":"de"},"boundingbox":["50.6233010","50.6434188","7.9086711","7.9342418"]}]