[{"place_id":143787741,"licence":"Data © OpenStreetMap contributors, ODbL 1.0. http://osm.org/copyright","osm_type":"relation","osm_id":4456134,"lat":"52.2643186","lon":"10.2069678","category":"boundary","type":"administrative","place_rank":18,"importance":0.26704010519783294,"addresstype":"village","name":"Ölsburg","display_name":"Ölsburg, Ilsede, Landkreis Peine, Lower Saxony, Germany","address":{"village":"Ölsburg","town":"Ilsede","county":"Landkreis Peine","state":"Lower Saxony","ISO3166-2-lvl4":"DE-NI","country":"Germany","country_code":"de"},"boundingbox":["52.2453255","52.2784262","10.1745678","10.2162671"]}]