[{"place_id":80190323,"licence":"Data © OpenStreetMap contributors, ODbL 1.0. http://osm.org/copyright","osm_type":"relation","osm_id":40568,"lat":"40.5302405","lon":"15.1310307","category":"boundary","type":"administrative","place_rank":16,"importance":0.5540352437840198,"addresstype":"village","name":"Altavilla Silentina","display_name":"Altavilla Silentina, Salerno, Campania, 84045, Italy","address":{"village":"Altavilla Silentina","county":"Salerno","ISO3166-2-lvl6":"IT-SA","state":"Campania","ISO3166-2-lvl4":"IT-72","postcode":"84045","country":"Italy","country_code":"it"},"boundingbox":["40.4982490","40.5617523","15.0434306","15.1892824"]}]